networkinglib/__init__.py
networkinglib/networkinglib.py
networkinglib-0.2.7.dist-info/LICENSE
networkinglib-0.2.7.dist-info/METADATA
networkinglib-0.2.7.dist-info/WHEEL
networkinglib-0.2.7.dist-info/top_level.txt
networkinglib-0.2.7.dist-info/RECORD
