Metadata-Version: 2.1
Name: networkinglib
Version: 0.2.7
Summary: Extension providing a basic networking protcol implementations as a Python module using mainly C-Extenstions.
Home-page: https://github.com/lstuma/networkinglib/
Author: lstuma
Author-email: g.lstuma@gmail.com
Classifier: License :: OSI Approved :: MIT License
Requires-Python: >=3.7
License-File: LICENSE
Requires-Dist: networking-tcp-client
Requires-Dist: networking-udp-client
